.coveragerc
.editorconfig
.pylintrc
.travis.yml
AUTHORS
ChangeLog
LICENSE
Makefile
Pipfile
README.rst
appveyor.yml
requirements-dev.txt
requirements.txt
setup.cfg
setup.py
tox.ini
doc/Makefile
doc/make.bat
doc/source/conf.py
doc/source/index.rst
txrwlock/__init__.py
txrwlock/txrwlock.py
txrwlock/txtestcase.py
txrwlock.egg-info/PKG-INFO
txrwlock.egg-info/SOURCES.txt
txrwlock.egg-info/dependency_links.txt
txrwlock.egg-info/not-zip-safe
txrwlock.egg-info/pbr.json
txrwlock.egg-info/requires.txt
txrwlock.egg-info/top_level.txt
txrwlock/tests/__init__.py
txrwlock/tests/test_txrwlock.py